mewarizz-0.0.5.dist-info/licenses/LICENSE
rizzler/__init__.py
mewarizz-0.0.5.dist-info/METADATA
mewarizz-0.0.5.dist-info/WHEEL
mewarizz-0.0.5.dist-info/top_level.txt
mewarizz-0.0.5.dist-info/RECORD
